infoeqv/__init__.py
infoeqv-6.0.5.dist-info/licenses/LICENSE
infoeqv-6.0.5.dist-info/METADATA
infoeqv-6.0.5.dist-info/WHEEL
infoeqv-6.0.5.dist-info/top_level.txt
infoeqv-6.0.5.dist-info/RECORD
