Metadata-Version: 2.4
Name: infoeqv
Version: 6.0.5
Summary: Information Equivalent Designs (Two-Point Reduction)
Home-page: https://github.com/muinrohit/infoeqv
Author: Rohit Kumar Behera
Author-email: rohitmbl24@gmail.com
License: MIT
Classifier: Programming Language :: Python :: 3
Classifier: License :: OSI Approved :: MIT License
Classifier: Operating System :: OS Independent
Requires-Python: >=3.6
License-File: LICENSE
Requires-Dist: numpy
Dynamic: author
Dynamic: author-email
Dynamic: classifier
Dynamic: description
Dynamic: description-content-type
Dynamic: home-page
Dynamic: license
Dynamic: license-file
Dynamic: requires-dist
Dynamic: requires-python
Dynamic: summary
